database_views/__init__.py
database_views/apps.py
database_views/mixins.py
database_views/models.py
database_views/response.py
database_views/urls.py
database_views/views.py
django_database_views-0.1.2.dist-info/DESCRIPTION.rst
django_database_views-0.1.2.dist-info/METADATA
django_database_views-0.1.2.dist-info/RECORD
django_database_views-0.1.2.dist-info/WHEEL
django_database_views-0.1.2.dist-info/metadata.json
django_database_views-0.1.2.dist-info/top_level.txt
