Metadata-Version: 2.0
Name: django-database-views
Version: 0.1.2
Summary: Django class based views for templates stored in a database.
Home-page: https://github.com/a7madnassar/django-database-views
Author: Ahmed Nassar
Author-email: ektebli@yahoo.com
License: BSD
Keywords: django-database-views
Platform: UNKNOWN
Classifier: Development Status :: 3 - Alpha
Classifier: Framework :: Django
Classifier: Framework :: Django :: 1.8
Classifier: Framework :: Django :: 1.9
Classifier: Framework :: Django :: 1.10
Classifier: Intended Audience :: Developers
Classifier: License :: OSI Approved :: BSD License
Classifier: Natural Language :: English
Classifier: Programming Language :: Python :: 2
Classifier: Programming Language :: Python :: 2.7
Classifier: Programming Language :: Python :: 3
Classifier: Programming Language :: Python :: 3.6
